medmolnet/__init__.py
medmolnet/data.py
medmolnet/data_main.py
medmolnet/example.py
medmolnet/interactive.py
medmolnet/interactive_main.py
medmolnet/string_api.py
bio_network_ayelet_tohar-0.1.2.dist-info/LICENSE
bio_network_ayelet_tohar-0.1.2.dist-info/METADATA
bio_network_ayelet_tohar-0.1.2.dist-info/WHEEL
bio_network_ayelet_tohar-0.1.2.dist-info/top_level.txt
bio_network_ayelet_tohar-0.1.2.dist-info/RECORD
