Metadata-Version: 2.1
Name: bio-network-ayelet-tohar
Version: 0.1.2
Summary: create sub networks
Home-page: https://github.com/Tohar-Ts/Towards-personalized-medicine-in-cancer
Author: Tohar&Ayelet
Author-email: ayelet gibly <ayelet47654@gmail.com>, tohar tsvitman <toharbk@gmail.com>
Project-URL: Bug Tracker, https://github.com/Tohar-Ts/Towards-personalized-medicine-in-cancer/issues
Classifier: Programming Language :: Python :: 3
Classifier: License :: OSI Approved :: MIT License
Classifier: Operating System :: OS Independent
Requires-Python: >=3.6
License-File: LICENSE
Provides-Extra: dev
Requires-Dist: tox ; extra == 'dev'
Requires-Dist: pre-commit ; extra == 'dev'
Requires-Dist: bump2version ; extra == 'dev'
